AUTHORS
LICENSE
MANIFEST.in
README.rst
RELEASE-VERSION
setup.py
docs/columns.rst
docs/netprofiler.rst
docs/overview.rst
docs/toc.rst
docs/tutorial.rst
examples/alerter.py
examples/devices.py
examples/flowlist.py
examples/identity_report.py
examples/import_hostgroups.py
examples/myreport.py
examples/percentile.py
examples/service_byloc.py
examples/template_report.py
examples/timeseries.py
examples/top_ports.py
examples/top_ports_time.py
examples/traffic_flowlist.py
examples/traffic_host_timeseries.py
examples/traffic_summary.py
examples/traffic_timeseries.py
examples/traffic_to_hostgroup.py
examples/wan_report.py
gitpy_versioning/__init__.py
notebooks/06-traffic-timeseries.ipynb
notebooks/07-import-hostgroups.ipynb
notebooks/08-netprofiler-and-netshark.ipynb
steelscript/__init__.py
steelscript.netprofiler.egg-info/PKG-INFO
steelscript.netprofiler.egg-info/SOURCES.txt
steelscript.netprofiler.egg-info/dependency_links.txt
steelscript.netprofiler.egg-info/entry_points.txt
steelscript.netprofiler.egg-info/namespace_packages.txt
steelscript.netprofiler.egg-info/requires.txt
steelscript.netprofiler.egg-info/top_level.txt
steelscript/netprofiler/__init__.py
steelscript/netprofiler/appfwk/__init__.py
steelscript/netprofiler/appfwk/models.py
steelscript/netprofiler/appfwk/plugin.py
steelscript/netprofiler/appfwk/datasources/__init__.py
steelscript/netprofiler/appfwk/datasources/netprofiler.py
steelscript/netprofiler/appfwk/datasources/netprofiler_devices.py
steelscript/netprofiler/appfwk/datasources/netprofiler_live.py
steelscript/netprofiler/appfwk/devices/__init__.py
steelscript/netprofiler/appfwk/devices/netprofiler.py
steelscript/netprofiler/appfwk/libs/__init__.py
steelscript/netprofiler/appfwk/libs/profiler_tools.py
steelscript/netprofiler/appfwk/reports/__init__.py
steelscript/netprofiler/appfwk/reports/netprofiler.py
steelscript/netprofiler/appfwk/reports/netprofiler_alert.py
steelscript/netprofiler/appfwk/reports/netprofiler_devices.py
steelscript/netprofiler/appfwk/reports/netprofiler_hostgroup.py
steelscript/netprofiler/appfwk/reports/netprofiler_hostgroup_general.py
steelscript/netprofiler/appfwk/reports/netprofiler_live.py
steelscript/netprofiler/appfwk/reports/netprofiler_service_by_loc.py
steelscript/netprofiler/appfwk/reports/netprofiler_top_n_time.py
