Metadata-Version: 2.1
Name: steelscript.netprofiler
Version: 2.0
Summary: Python module for interacting with Riverbed NetProfiler with SteelScript
Home-page: http://pythonhosted.org/steelscript
Author: Riverbed Technology
Author-email: eng-github@riverbed.com
License: MIT
Platform: Linux
Platform: Mac OS
Platform: Windows
Classifier: Development Status :: 4 - Beta
Classifier: Intended Audience :: Developers
Classifier: Intended Audience :: Information Technology
Classifier: Intended Audience :: System Administrators
Classifier: License :: OSI Approved :: MIT License
Classifier: Programming Language :: Python :: 3.5
Classifier: Topic :: System :: Networking
Requires-Python: >3.5.0
Provides-Extra: test
